[{"url":"http://oooooo.oss-cn-fuzhou.aliyuncs.com/blog/202310121704067.jpg","alt":"202310121704067.jpg","title":"202310121704067.jpg"},{"url":"http://oooooo.oss-cn-fuzhou.aliyuncs.com/blog/202310121723240.jpg","alt":"202310121723240.jpg","title":"202310121723240.jpg"},{"url":"http://oooooo.oss-cn-fuzhou.aliyuncs.com/blog/202310121723242.jpg","alt":"202310121723242.jpg","title":"202310121723242.jpg"},{"url":"http://oooooo.oss-cn-fuzhou.aliyuncs.com/blog/202310121723243.jpg","alt":"202310121723243.jpg","title":"202310121723243.jpg"},{"url":"http://oooooo.oss-cn-fuzhou.aliyuncs.com/blog/202310121723244.jpg","alt":"202310121723244.jpg","title":"202310121723244.jpg"},{"url":"http://oooooo.oss-cn-fuzhou.aliyuncs.com/blog/202310121723245.jpg","alt":"202310121723245.jpg","title":"202310121723245.jpg"},{"url":"http://oooooo.oss-cn-fuzhou.aliyuncs.com/blog/202310121723246.jpg","alt":"202310121723246.jpg","title":"202310121723246.jpg"},{"url":"http://oooooo.oss-cn-fuzhou.aliyuncs.com/blog/202310121723247.jpg","alt":"202310121723247.jpg","title":"202310121723247.jpg"}]